{ "frames": [
   {
    "filename": "puppy 0.aseprite",
    "frame": { "x": 1, "y": 1, "w": 18, "h": 18 },
    "rotated": false,
    "trimmed": false,
    "spriteSourceSize": { "x": 0, "y": 0, "w": 18, "h": 18 },
    "sourceSize": { "w": 18, "h": 18 },
    "duration": 100
   },
   {
    "filename": "puppy 1.aseprite",
    "frame": { "x": 1, "y": 19, "w": 18, "h": 18 },
    "rotated": false,
    "trimmed": false,
    "spriteSourceSize": { "x": 0, "y": 0, "w": 18, "h": 18 },
    "sourceSize": { "w": 18, "h": 18 },
    "duration": 100
   },
   {
    "filename": "puppy 2.aseprite",
    "frame": { "x": 1, "y": 37, "w": 18, "h": 18 },
    "rotated": false,
    "trimmed": false,
    "spriteSourceSize": { "x": 0, "y": 0, "w": 18, "h": 18 },
    "sourceSize": { "w": 18, "h": 18 },
    "duration": 100
   },
   {
    "filename": "puppy 3.aseprite",
    "frame": { "x": 19, "y": 1, "w": 18, "h": 18 },
    "rotated": false,
    "trimmed": false,
    "spriteSourceSize": { "x": 0, "y": 0, "w": 18, "h": 18 },
    "sourceSize": { "w": 18, "h": 18 },
    "duration": 100
   },
   {
    "filename": "puppy 4.aseprite",
    "frame": { "x": 19, "y": 19, "w": 18, "h": 18 },
    "rotated": false,
    "trimmed": false,
    "spriteSourceSize": { "x": 0, "y": 0, "w": 18, "h": 18 },
    "sourceSize": { "w": 18, "h": 18 },
    "duration": 100
   },
   {
    "filename": "puppy 5.aseprite",
    "frame": { "x": 19, "y": 37, "w": 18, "h": 18 },
    "rotated": false,
    "trimmed": false,
    "spriteSourceSize": { "x": 0, "y": 0, "w": 18, "h": 18 },
    "sourceSize": { "w": 18, "h": 18 },
    "duration": 100
   },
   {
    "filename": "puppy 6.aseprite",
    "frame": { "x": 37, "y": 1, "w": 18, "h": 18 },
    "rotated": false,
    "trimmed": false,
    "spriteSourceSize": { "x": 0, "y": 0, "w": 18, "h": 18 },
    "sourceSize": { "w": 18, "h": 18 },
    "duration": 100
   },
   {
    "filename": "puppy 7.aseprite",
    "frame": { "x": 37, "y": 19, "w": 18, "h": 18 },
    "rotated": false,
    "trimmed": false,
    "spriteSourceSize": { "x": 0, "y": 0, "w": 18, "h": 18 },
    "sourceSize": { "w": 18, "h": 18 },
    "duration": 100
   },
   {
    "filename": "puppy 8.aseprite",
    "frame": { "x": 37, "y": 37, "w": 18, "h": 18 },
    "rotated": false,
    "trimmed": false,
    "spriteSourceSize": { "x": 0, "y": 0, "w": 18, "h": 18 },
    "sourceSize": { "w": 18, "h": 18 },
    "duration": 100
   }
 ],
 "meta": {
  "app": "http://www.aseprite.org/",
  "version": "1.2.29",
  "image": "puppy.png",
  "format": "RGBA8888",
  "size": { "w": 56, "h": 66 },
  "scale": "1",
  "frameTags": [
   { "name": "idle", "from": 0, "to": 0, "direction": "forward" },
   { "name": "riding-up", "from": 1, "to": 1, "direction": "forward" },
   { "name": "riding-mid", "from": 2, "to": 2, "direction": "forward" },
   { "name": "riding-down", "from": 3, "to": 3, "direction": "forward" },
   { "name": "run", "from": 4, "to": 5, "direction": "forward" },
   { "name": "jump-up", "from": 6, "to": 6, "direction": "forward" },
   { "name": "jump-mid", "from": 7, "to": 7, "direction": "forward" },
   { "name": "jump-down", "from": 8, "to": 8, "direction": "forward" }
  ]
 }
}
